{"timestamp": "2018-07-28T03:00:00", "edges": [{"bad_volume": 0, "from_ip": "prodcompworker1b.prod.addepar.com", "to_ip": "sms.addepar.com", "warning_volume": 0, "good_volume": 0.0}, {"bad_volume": 0, "from_ip": "prodcompworker3a.prod.addepar.com", "to_ip": "sms.addepar.com", "warning_volume": 0, "good_volume": 0.0}, {"bad_volume": 0, "from_ip": "prodcompa1.prod.addepar.com", "to_ip": "sms.addepar.com", "warning_volume": 0, "good_volume": 1249.7237569060774}, {"bad_volume": 0, "from_ip": "prodcompd3.prod.addepar.com", "to_ip": "sms.addepar.com", "warning_volume": 0, "good_volume": 0.0}, {"bad_volume": 0, "from_ip": "prodcompc4.prod.addepar.com", "to_ip": "sms.addepar.com", "warning_volume": 0, "good_volume": 0.0}, {"bad_volume": 0, "from_ip": "prodcompworker4b.prod.addepar.com", "to_ip": "sms.addepar.com", "warning_volume": 0, "good_volume": 1.3259668508287292}, {"bad_volume": 0, "from_ip": "prodcompworker2a.prod.addepar.com", "to_ip": "sms.addepar.com", "warning_volume": 0, "good_volume": 237.01657458563534}, {"bad_volume": 0, "from_ip": "prodcompworker2b.prod.addepar.com", "to_ip": "sms.addepar.com", "warning_volume": 0, "good_volume": 0.0}, {"bad_volume": 0, "from_ip": "prodcompc2.prod.addepar.com", "to_ip": "sms.addepar.com", "warning_volume": 0, "good_volume": 0.0}, {"bad_volume": 0, "from_ip": "prodcompa2.prod.addepar.com", "to_ip": "sms.addepar.com", "warning_volume": 0, "good_volume": 3303.314917127072}, {"bad_volume": 0, "from_ip": "prodcompworker3b.prod.addepar.com", "to_ip": "sms.addepar.com", "warning_volume": 0, "good_volume": 0.0}, {"bad_volume": 0, "from_ip": "prodcompd4.prod.addepar.com", "to_ip": "sms.addepar.com", "warning_volume": 0, "good_volume": 0.0}, {"bad_volume": 0, "from_ip": "prodcompb2.prod.addepar.com", "to_ip": "sms.addepar.com", "warning_volume": 0, "good_volume": 3368.28729281768}, {"bad_volume": 0, "from_ip": "prodcompworker4a.prod.addepar.com", "to_ip": "sms.addepar.com", "warning_volume": 0, "good_volume": 0.0}, {"bad_volume": 0, "from_ip": "prodcompa4.prod.addepar.com", "to_ip": "sms.addepar.com", "warning_volume": 0, "good_volume": 553.9226519337016}, {"bad_volume": 0, "from_ip": "prodcompd1.prod.addepar.com", "to_ip": "sms.addepar.com", "warning_volume": 0, "good_volume": 0.0}, {"bad_volume": 0, "from_ip": "prodcompb3.prod.addepar.com", "to_ip": "sms.addepar.com", "warning_volume": 0, "good_volume": 16.243093922651934}, {"bad_volume": 0, "from_ip": "prodcompworker1a.prod.addepar.com", "to_ip": "sms.addepar.com", "warning_volume": 0, "good_volume": 0.0}, {"bad_volume": 0, "from_ip": "prodcompd2.prod.addepar.com", "to_ip": "sms.addepar.com", "warning_volume": 0, "good_volume": 0.0}, {"bad_volume": 0, "from_ip": "prodcompb1.prod.addepar.com", "to_ip": "sms.addepar.com", "warning_volume": 0, "good_volume": 1373.3701657458564}, {"bad_volume": 0, "from_ip": "prodcompc3.prod.addepar.com", "to_ip": "sms.addepar.com", "warning_volume": 0, "good_volume": 6.101694915254238}, {"bad_volume": 0, "from_ip": "prodcompa3.prod.addepar.com", "to_ip": "sms.addepar.com", "warning_volume": 0, "good_volume": 1524.5303867403316}, {"bad_volume": 0, "from_ip": "prodcompb4.prod.addepar.com", "to_ip": "sms.addepar.com", "warning_volume": 0, "good_volume": 0.0}, {"bad_volume": 0, "from_ip": "prodcompc1.prod.addepar.com", "to_ip": "sms.addepar.com", "warning_volume": 0, "good_volume": 0.0}]}