{"timestamp": "2018-07-28T05:00:00", "edges": [{"bad_volume": 0, "from_ip": "prodcompc4.prod.addepar.com", "to_ip": "prodcompworker3a.prod.addepar.com", "warning_volume": 0, "good_volume": 3}, {"bad_volume": 0, "from_ip": "prodcompb4.prod.addepar.com", "to_ip": "prodcompworker4a.prod.addepar.com", "warning_volume": 0, "good_volume": 85}, {"bad_volume": 0, "from_ip": "prodcompb2.prod.addepar.com", "to_ip": "prodcompworker3a.prod.addepar.com", "warning_volume": 0, "good_volume": 164}, {"bad_volume": 0, "from_ip": "prodcompb4.prod.addepar.com", "to_ip": "prodcompworker1b.prod.addepar.com", "warning_volume": 0, "good_volume": 66}, {"bad_volume": 0, "from_ip": "prodcompb4.prod.addepar.com", "to_ip": "prodcompworker2b.prod.addepar.com", "warning_volume": 0, "good_volume": 41}, {"bad_volume": 0, "from_ip": "prodcompb4.prod.addepar.com", "to_ip": "prodcompworker4b.prod.addepar.com", "warning_volume": 0, "good_volume": 33}, {"bad_volume": 0, "from_ip": "prodcompb4.prod.addepar.com", "to_ip": "prodcompworker3b.prod.addepar.com", "warning_volume": 0, "good_volume": 34}, {"bad_volume": 0, "from_ip": "prodcompb1.prod.addepar.com", "to_ip": "prodcompworker3b.prod.addepar.com", "warning_volume": 0, "good_volume": 51}, {"bad_volume": 0, "from_ip": "prodcompb4.prod.addepar.com", "to_ip": "prodcompworker1a.prod.addepar.com", "warning_volume": 0, "good_volume": 19}, {"bad_volume": 0, "from_ip": "prodcompb2.prod.addepar.com", "to_ip": "prodcompworker1a.prod.addepar.com", "warning_volume": 0, "good_volume": 15}, {"bad_volume": 0, "from_ip": "prodcompb4.prod.addepar.com", "to_ip": "prodcompworker2a.prod.addepar.com", "warning_volume": 0, "good_volume": 22}, {"bad_volume": 0, "from_ip": "prodcompc4.prod.addepar.com", "to_ip": "prodcompworker2b.prod.addepar.com", "warning_volume": 0, "good_volume": 3}, {"bad_volume": 0, "from_ip": "prodcompc1.prod.addepar.com", "to_ip": "prodcompworker1b.prod.addepar.com", "warning_volume": 0, "good_volume": 3}, {"bad_volume": 0, "from_ip": "prodcompc1.prod.addepar.com", "to_ip": "prodcompworker3a.prod.addepar.com", "warning_volume": 0, "good_volume": 3}, {"bad_volume": 0, "from_ip": "prodcompb2.prod.addepar.com", "to_ip": "prodcompworker4b.prod.addepar.com", "warning_volume": 0, "good_volume": 159}, {"bad_volume": 0, "from_ip": "prodcompb3.prod.addepar.com", "to_ip": "prodcompworker4b.prod.addepar.com", "warning_volume": 0, "good_volume": 64}, {"bad_volume": 0, "from_ip": "prodcompb2.prod.addepar.com", "to_ip": "prodcompworker2b.prod.addepar.com", "warning_volume": 0, "good_volume": 95}, {"bad_volume": 0, "from_ip": "prodcompb3.prod.addepar.com", "to_ip": "prodcompworker1b.prod.addepar.com", "warning_volume": 0, "good_volume": 8}, {"bad_volume": 0, "from_ip": "prodcompc1.prod.addepar.com", "to_ip": "prodcompworker4a.prod.addepar.com", "warning_volume": 0, "good_volume": 3}, {"bad_volume": 0, "from_ip": "prodcompb3.prod.addepar.com", "to_ip": "prodcompworker1a.prod.addepar.com", "warning_volume": 0, "good_volume": 30}, {"bad_volume": 0, "from_ip": "prodcompb3.prod.addepar.com", "to_ip": "prodcompworker3b.prod.addepar.com", "warning_volume": 0, "good_volume": 81}, {"bad_volume": 0, "from_ip": "prodcompb1.prod.addepar.com", "to_ip": "prodcompworker2a.prod.addepar.com", "warning_volume": 0, "good_volume": 35}, {"bad_volume": 0, "from_ip": "prodcompb1.prod.addepar.com", "to_ip": "prodcompworker4b.prod.addepar.com", "warning_volume": 0, "good_volume": 40}, {"bad_volume": 0, "from_ip": "prodcompb1.prod.addepar.com", "to_ip": "prodcompworker3a.prod.addepar.com", "warning_volume": 0, "good_volume": 91}, {"bad_volume": 0, "from_ip": "prodcompb1.prod.addepar.com", "to_ip": "prodcompworker1b.prod.addepar.com", "warning_volume": 0, "good_volume": 67}, {"bad_volume": 0, "from_ip": "prodcompb1.prod.addepar.com", "to_ip": "prodcompworker1a.prod.addepar.com", "warning_volume": 0, "good_volume": 45}, {"bad_volume": 0, "from_ip": "prodcompc4.prod.addepar.com", "to_ip": "prodcompworker4a.prod.addepar.com", "warning_volume": 0, "good_volume": 3}, {"bad_volume": 0, "from_ip": "prodcompb1.prod.addepar.com", "to_ip": "prodcompworker2b.prod.addepar.com", "warning_volume": 0, "good_volume": 33}, {"bad_volume": 0, "from_ip": "prodcompb3.prod.addepar.com", "to_ip": "prodcompworker2a.prod.addepar.com", "warning_volume": 0, "good_volume": 20}, {"bad_volume": 0, "from_ip": "prodcompb2.prod.addepar.com", "to_ip": "prodcompworker2a.prod.addepar.com", "warning_volume": 0, "good_volume": 11}, {"bad_volume": 0, "from_ip": "prodcompb3.prod.addepar.com", "to_ip": "prodcompworker4a.prod.addepar.com", "warning_volume": 0, "good_volume": 25}, {"bad_volume": 0, "from_ip": "prodcompb2.prod.addepar.com", "to_ip": "prodcompworker3b.prod.addepar.com", "warning_volume": 0, "good_volume": 35}, {"bad_volume": 0, "from_ip": "prodcompb4.prod.addepar.com", "to_ip": "prodcompworker3a.prod.addepar.com", "warning_volume": 0, "good_volume": 86}, {"bad_volume": 0, "from_ip": "prodcompb3.prod.addepar.com", "to_ip": "prodcompworker2b.prod.addepar.com", "warning_volume": 0, "good_volume": 5}, {"bad_volume": 0, "from_ip": "prodcompb2.prod.addepar.com", "to_ip": "prodcompworker1b.prod.addepar.com", "warning_volume": 0, "good_volume": 90}, {"bad_volume": 0, "from_ip": "prodcompb1.prod.addepar.com", "to_ip": "prodcompworker4a.prod.addepar.com", "warning_volume": 0, "good_volume": 82}, {"bad_volume": 0, "from_ip": "prodcompb3.prod.addepar.com", "to_ip": "prodcompworker3a.prod.addepar.com", "warning_volume": 0, "good_volume": 61}, {"bad_volume": 0, "from_ip": "prodcompc1.prod.addepar.com", "to_ip": "prodcompworker2b.prod.addepar.com", "warning_volume": 0, "good_volume": 3}, {"bad_volume": 0, "from_ip": "prodcompc4.prod.addepar.com", "to_ip": "prodcompworker1b.prod.addepar.com", "warning_volume": 0, "good_volume": 3}, {"bad_volume": 0, "from_ip": "prodcompb2.prod.addepar.com", "to_ip": "prodcompworker4a.prod.addepar.com", "warning_volume": 0, "good_volume": 35}]}